mcphero/__about__.py
mcphero/__init__.py
mcphero/exceptions.py
mcphero/adapters/__init__.py
mcphero/adapters/base_adapter.py
mcphero/adapters/gemini.py
mcphero/adapters/openai.py
mcphero-0.2.1.dist-info/METADATA
mcphero-0.2.1.dist-info/WHEEL
mcphero-0.2.1.dist-info/licenses/LICENSE
mcphero-0.2.1.dist-info/RECORD
