Metadata-Version: 2.4
Name: mcphero
Version: 0.2.1
Summary: Library to use MCP servers natively with AI clients as tools.
Project-URL: Homepage, https://github.com/stepacool/mcphero
Project-URL: Documentation, https://mcphero.app/docs
Project-URL: Issues, https://github.com/stepacool/mcphero/issues
Project-URL: Website, https://mcphero.app
Author-email: Stepan Filonov <stepanfilonov@gmail.com>
License-File: LICENSE
Keywords: llm clients,mcp,mcp client,openai,tool calling
Classifier: Development Status :: 3 - Alpha
Classifier: Framework :: AsyncIO
Classifier: Intended Audience :: Developers
Classifier: License :: OSI Approved :: MIT License
Classifier: Operating System :: OS Independent
Classifier: Programming Language :: Python
Classifier: Programming Language :: Python :: 3
Classifier: Programming Language :: Python :: 3 :: Only
Classifier: Programming Language :: Python :: 3.9
Classifier: Programming Language :: Python :: 3.10
Classifier: Programming Language :: Python :: 3.11
Classifier: Programming Language :: Python :: Implementation :: CPython
Classifier: Topic :: Software Development :: Libraries :: Python Modules
Classifier: Topic :: System :: Networking
Classifier: Typing :: Typed
Requires-Python: >=3.9
Requires-Dist: httpx
Requires-Dist: openai
Provides-Extra: google-genai
Requires-Dist: google-genai; extra == 'google-genai'
